gentccode/__init__.py
gentccode/cartesian.py
gentccode/check_version.py
gentccode/cli.py
gentccode/compose_code.py
gentccode/convert_to_jmx.py
gentccode/convert_to_locust.py
gentccode/filter_cp_result.py
gentccode/generate_code.py
gentccode/merge_api.py
gentccode/payload_cartesian_product.py
gentccode/read_swagger_rule.py
gentccode/save_code_to_file.py
gentccode/url_parse.py
gentccode-0.3.6.dist-info/METADATA
gentccode-0.3.6.dist-info/WHEEL
gentccode-0.3.6.dist-info/entry_points.txt
gentccode-0.3.6.dist-info/licenses/LICENSE
gentccode-0.3.6.dist-info/RECORD
