Metadata-Version: 2.4
Name: gentccode
Version: 0.3.6
Summary: generate test case code
License-File: LICENSE
Author: leo
Requires-Python: >=3.9,<4.0
Classifier: License :: OSI Approved :: MIT License
Classifier: Operating System :: OS Independent
Classifier: Programming Language :: Python :: 3
Classifier: Programming Language :: Python :: 3.9
Classifier: Programming Language :: Python :: 3.10
Classifier: Programming Language :: Python :: 3.11
Classifier: Programming Language :: Python :: 3.12
Classifier: Programming Language :: Python :: 3.13
Classifier: Programming Language :: Python :: 3.14
Requires-Dist: click (>=8.1.7,<9.0.0)
Requires-Dist: http-content-parser (>=0.0.26,<0.0.27)
Requires-Dist: lxml (>=5.2.2,<6.0.0)
Requires-Dist: packaging (>=22.0)
Requires-Dist: pyyaml (>=6.0,<7.0)
